caipirinha_cmdtools
