Metadata-Version: 1.2
Name: caipirinha-cmdtools
Version: 0.6.0
Summary: Collection of command-line tools
Home-page: https://github.com/rbrecheisen/caipirinha_cmdtools
Author: Ralph Brecheisen
Author-email: ralph.brecheisen@gmail.com
License: MIT license
Keywords: caipirinha_cmdtools
Platform: UNKNOWN
Classifier: Development Status :: 2 - Pre-Alpha
Classifier: Intended Audience :: Developers
Classifier: License :: OSI Approved :: MIT License
Classifier: Natural Language :: English
Classifier: Programming Language :: Python :: 3
Classifier: Programming Language :: Python :: 3.5
Classifier: Programming Language :: Python :: 3.6
Classifier: Programming Language :: Python :: 3.7
Classifier: Programming Language :: Python :: 3.8
Requires-Python: >=3.5
